mysqlcipher
