Metadata-Version: 2.1
Name: mysqlcipher
Version: 0.1.3
Summary: DB-API 2.0 interface for SQLCipher 4.x
Home-page: https://github.com/jo-project/mysqlcipher
Author: jo-project
Author-email: jo.project.0911@gmail.com
License: zlib/libpng
Platform: ALL
Classifier: Development Status :: 4 - Beta
Classifier: Intended Audience :: Developers
Classifier: License :: OSI Approved :: zlib/libpng License
Classifier: Operating System :: MacOS :: MacOS X
Classifier: Operating System :: Microsoft :: Windows
Classifier: Operating System :: POSIX
Classifier: Programming Language :: C
Classifier: Programming Language :: Python
Classifier: Topic :: Database :: Database Engines/Servers
Classifier: Topic :: Software Development :: Libraries :: Python Modules
License-File: LICENSE
